{
  "posts": [
    {
      "id": 1,
      "title": " 수정내용 6",
      "complete": false
    },
    {
      "id": 3,
      "title": "힘내 10",
      "complete": true
    },
    {
      "id": 2,
      "title": "추가내용",
      "complete": true
    },
    {
      "id": 6,
      "title": "추가내용7",
      "complete": true
    },
    {
      "id": 7,
      "title": "추가내용8",
      "complete": true
    },
    {
      "id": 1685414252181,
      "title": "추가내용5",
      "complete": true
    },
    {
      "id": 1685414262509,
      "title": "추가내용5",
      "complete": true
    },
    {
      "id": 1685414277277,
      "title": "추가내용5",
      "complete": true
    },
    {
      "id": 1685415324087,
      "title": "추가내용5",
      "complete": true
    },
    {
      "id": 1685415325111,
      "title": "추가내용6",
      "complete": true
    },
    {
      "id": 1685415326439,
      "title": "추가내용7",
      "complete": true
    },
    {
      "id": 1685415395023,
      "title": "추가내용5",
      "complete": true
    },
    {
      "id": 1685415442919,
      "title": "추가내용5",
      "complete": true
    },
    {
      "id": 1685415443263,
      "title": "추가내용6",
      "complete": true
    },
    {
      "id": 1685415443927,
      "title": "추가내용7",
      "complete": true
    },
    {
      "id": 1685415472247,
      "title": "추가내용8",
      "complete": true
    },
    {
      "id": 1685415476975,
      "title": "추가내용5",
      "complete": true
    },
    {
      "id": 1685415480360,
      "title": "추가내용7",
      "complete": true
    },
    {
      "id": 1685415482288,
      "title": "추가내용5",
      "complete": true
    },
    {
      "id": 1685415482735,
      "title": "추가내용6",
      "complete": true
    }
  ],
  "comments": [
    {
      "id": 1,
      "body": "some comment",
      "postId": 1
    }
  ],
  "profile": {
    "name": "typicode"
  }
}